gtkml/.DS_Store
gtkml/__init__.py
gtkml/model.py
gtkml-0.0.2.dist-info/METADATA
gtkml-0.0.2.dist-info/WHEEL
gtkml-0.0.2.dist-info/licenses/LICENSE
gtkml-0.0.2.dist-info/RECORD
