Metadata-Version: 2.1
Name: gtkml
Version: 0.0.2
Summary: LabNeura - A Python package for neural network experiments
Project-URL: Homepage, https://github.com/tharungoka/LabNeura
Project-URL: Issues, https://github.com/tharungoka/LabNeura/issues
Author-email: Goka Tharun Kumar <tharunkumargoka2020@gmail.com>
License-File: LICENSE
Classifier: License :: OSI Approved :: MIT License
Classifier: Operating System :: OS Independent
Classifier: Programming Language :: Python :: 3
Requires-Python: >=3.8
